AUTHORS.rst
CONTRIBUTING.rst
HISTORY.rst
LICENSE
MANIFEST.in
README.rst
setup.cfg
setup.py
docs/Makefile
docs/authors.rst
docs/conf.py
docs/contributing.rst
docs/examples.rst
docs/history.rst
docs/index.rst
docs/installation.rst
docs/make.bat
docs/readme.rst
docs/reference.rst
docs/usage.rst
docs/zbibliography.rst
docs/_templates/template_module.rst
inferno/__init__.py
inferno/inferno.py
inferno/extensions/__init__.py
inferno/extensions/containers/__init__.py
inferno/extensions/containers/graph.py
inferno/extensions/containers/sequential.py
inferno/extensions/criteria/__init__.py
inferno/extensions/criteria/core.py
inferno/extensions/criteria/set_similarity_measures.py
inferno/extensions/initializers/__init__.py
inferno/extensions/initializers/base.py
inferno/extensions/initializers/presets.py
inferno/extensions/layers/__init__.py
inferno/extensions/layers/activations.py
inferno/extensions/layers/convolutional.py
inferno/extensions/layers/device.py
inferno/extensions/layers/reshape.py
inferno/extensions/metrics/__init__.py
inferno/extensions/metrics/arand.py
inferno/extensions/metrics/base.py
inferno/extensions/metrics/categorical.py
inferno/extensions/optimizers/__init__.py
inferno/extensions/optimizers/adam.py
inferno/extensions/optimizers/annealed_adam.py
inferno/io/__init__.py
inferno/io/box/__init__.py
inferno/io/box/camvid.py
inferno/io/box/cifar10.py
inferno/io/box/cityscapes.py
inferno/io/core/__init__.py
inferno/io/core/base.py
inferno/io/core/concatenate.py
inferno/io/core/data_utils.py
inferno/io/core/zip.py
inferno/io/transform/__init__.py
inferno/io/transform/base.py
inferno/io/transform/generic.py
inferno/io/transform/image.py
inferno/io/transform/volume.py
inferno/io/volumetric/__init__.py
inferno/io/volumetric/volume.py
inferno/io/volumetric/volumetric_utils.py
inferno/trainers/__init__.py
inferno/trainers/basic.py
inferno/trainers/callbacks/__init__.py
inferno/trainers/callbacks/base.py
inferno/trainers/callbacks/essentials.py
inferno_pytorch.egg-info/PKG-INFO
inferno_pytorch.egg-info/SOURCES.txt
inferno_pytorch.egg-info/dependency_links.txt
inferno_pytorch.egg-info/not-zip-safe
inferno_pytorch.egg-info/requires.txt
inferno_pytorch.egg-info/top_level.txt
