Metadata-Version: 1.1
Name: inferno-pytorch
Version: 0.1.7
Summary: Inferno is a little library providing utilities and convenience functions/classes around PyTorch.
Home-page: https://github.com/nasimrahaman/inferno
Author: Nasim Rahaman
Author-email: nasim.rahaman@iwr.uni-heidelberg.de
License: Apache Software License 2.0
Keywords: inferno pytorch torch deep learning cnn deep-pyromania
Platform: UNKNOWN
Classifier: Development Status :: 2 - Pre-Alpha
Classifier: Intended Audience :: Science/Research
Classifier: License :: OSI Approved :: Apache Software License
Classifier: Natural Language :: English
Classifier: Programming Language :: Python :: 3.5
Classifier: Programming Language :: Python :: 3.6
